potato_tool/__init__.py
potato_tool/font.py
potato_tool-0.0.6.dist-info/METADATA
potato_tool-0.0.6.dist-info/WHEEL
potato_tool-0.0.6.dist-info/entry_points.txt
potato_tool-0.0.6.dist-info/top_level.txt
potato_tool-0.0.6.dist-info/RECORD
