Metadata-Version: 2.1
Name: potato-tool
Version: 0.0.6
Summary: 输出染色、前置符、格式化输出及表格输出
Home-page: https://potato.gold
Author: Potato
Author-email: ljy1058318852@163.com
License: UNKNOWN
Platform: UNKNOWN
Requires-Dist: terminal
Requires-Dist: console
Requires-Dist: wcwidth
